django_bootstrap_breadcrumbs/__init__.py
django_bootstrap_breadcrumbs/templates/django_bootstrap_breadcrumbs/bootstrap2.html
django_bootstrap_breadcrumbs/templates/django_bootstrap_breadcrumbs/bootstrap3.html
django_bootstrap_breadcrumbs/templates/django_bootstrap_breadcrumbs/bootstrap4.html
django_bootstrap_breadcrumbs/templates/django_bootstrap_breadcrumbs/bootstrap5.html
django_bootstrap_breadcrumbs/templatetags/__init__.py
django_bootstrap_breadcrumbs/templatetags/django_bootstrap_breadcrumbs.py
django_bootstrap_breadcrumbs2-1.0.0.dist-info/LICENSE
django_bootstrap_breadcrumbs2-1.0.0.dist-info/METADATA
django_bootstrap_breadcrumbs2-1.0.0.dist-info/WHEEL
django_bootstrap_breadcrumbs2-1.0.0.dist-info/top_level.txt
django_bootstrap_breadcrumbs2-1.0.0.dist-info/RECORD
